<?xml version="1.0" encoding="ISO-8859-1" ?>

<azule>
	<object type="DatabaseTexture"/>

	<object type="EntityDatabase">
		<object type="Entity">
			<object type="TransformComponent">
				<property name="Position" value="{&quot;x&quot;: 32, &quot;y&quot;: 224}"/>
			</object>

			<object type="BoxSelectionComponent">
				<property name="Selected" value="true"/>
				<property name="Size" value="{&quot;x&quot;: 48, &quot;y&quot;: 50}"/>
				<property name="OutlineThickness" value="2.0"/>
				<property name="OutlineColor" value="[255, 0, 0, 255]"/>
				<property name="FillColor" value="[255, 0, 0, 150]"/>
			</object>
		</object>

		<!-- Tower -->
		<object type="Entity">
			<object type="TransformComponent">
				<property name="Position" value="{&quot;x&quot;: 160, &quot;y&quot;: 224}"/>
			</object>

			<object type="CircleCollisionComponent">
				<property name="Radius" value="100.0"/>
				<property name="IsSensor" value="true"/>
			</object>

			<object type="SpriteComponent">
				<property name="File" value="$AZULE_MAPS/towerDefense_tilesheet.png"/>
				<property name="HFrames" value="23"/>
				<property name="VFrames" value="13"/>
				<property name="Frame" value="135"/>
				<property name="Rotation" value="135.0"/>
			</object>
		</object>

		<object type="Entity">
			<object type="TransformComponent">
				<property name="Position" value="{&quot;x&quot;: 200, &quot;y&quot;: 270}"/>
			</object>

			<object type="SpriteComponent">
				<property name="File" value="$AZULE_MAPS/towerDefense_tilesheet.png"/>
				<property name="HFrames" value="23"/>
				<property name="VFrames" value="13"/>
				<property name="Frame" value="136"/>
				<property name="Rotation" value="135.0"/>
			</object>
		</object>
	</object>

	<object type="WaypointSystem"/>
	<object type="PhysicsSystem"/>

	<object type="CloneSystem">
		<property name="Rate" value="500000"/>
		<property name="Limit" value="400"/>

		<object type="Entity">
			<property name="reference" value="sprite"/>

			<object type="TransformComponent">
				<property name="Position" value="{&quot;x&quot;: 0, &quot;y&quot;: 325}"/>
			</object>

			<object type="ProgressBarComponent">
				<property name="Value" value="50"/>
				<property name="ValueMax" value="100"/>
				<property name="Position" value="{&quot;x&quot;: -15, &quot;y&quot;: -30}"/>
				<property name="Size" value="{&quot;x&quot;: 30, &quot;y&quot;: 5}"/>
				<property name="Color" value="[0, 255, 0, 255]"/>
				<property name="RenderOrder" value="1"/>
			</object>

			<object type="KinematicComponent">
				<property name="BodyType" value="Kinematic"/>
				<property name="LinearVelocity" value="{&quot;x&quot;: 50.0, &quot;y&quot;: 0.0}"/>
				<property name="CalculateHeading" value="true"/>
			</object>

			<object type="SpriteComponent" id="Cloned">
				<property name="File" value="$AZULE_MAPS/towerDefense_tilesheet.png"/>
				<property name="HFrames" value="23"/>
				<property name="VFrames" value="13"/>
				<property name="Frame" value="130"/>
				<property name="Rotation" value="-90.0"/>
			</object>

			<object type="WaypointComponent">
				<object type="Waypoint">
					<property name="Position" value="{&quot;x&quot;: 325, &quot;y&quot;: 325}"/>
				</object>
				<object type="Waypoint">
					<property name="Position" value="{&quot;x&quot;: 325, &quot;y&quot;: 125}"/>
				</object>
				<object type="Waypoint">
					<property name="Position" value="{&quot;x&quot;: 505, &quot;y&quot;: 125}"/>
				</object>
				<object type="Waypoint">
					<property name="Position" value="{&quot;x&quot;: 505, &quot;y&quot;: 575}"/>
				</object>
				<object type="Waypoint">
					<property name="Position" value="{&quot;x&quot;: 775, &quot;y&quot;: 575}"/>
				</object>
				<object type="Waypoint">
					<property name="Position" value="{&quot;x&quot;: 775, &quot;y&quot;: 325}"/>
				</object>
				<object type="Waypoint">
					<property name="Position" value="{&quot;x&quot;: 850, &quot;y&quot;: 325}"/>
				</object>
			</object>
		</object>
	</object>

	<object type="Window">
		<object type="TileMapSystem"/>
		<object type="RenderSystem"/>
		<object type="PhysicsRenderSystem"/>
	</object>
</azule>
